udt/__init__.py
udt/cli.py
udt/finder.py
udt/ls.py
udt/markdown.py
udt/srt.py
udt/translate.py
udt/yml.py
udt-0.5.dist-info/LICENSE
udt-0.5.dist-info/METADATA
udt-0.5.dist-info/WHEEL
udt-0.5.dist-info/entry_points.txt
udt-0.5.dist-info/top_level.txt
udt-0.5.dist-info/RECORD
