Metadata-Version: 2.1
Name: udt
Version: 0.5
Summary: udacity 翻译助手
Home-page: https://cn.udacity.com/
Author: 青笔
Author-email: kenbliky@gmail.com
License: MIT
Platform: UNKNOWN
Classifier: Programming Language :: Python :: 3
Classifier: License :: OSI Approved :: MIT License
Classifier: Operating System :: OS Independent
Requires-Python: >=3.6
Requires-Dist: PyYAML (>=5.1.2)
Requires-Dist: requests (>=2.22.0)
